MANIFEST.in
README.md
setup.py
./README.md
Finance_JindowinData.egg-info/PKG-INFO
Finance_JindowinData.egg-info/SOURCES.txt
Finance_JindowinData.egg-info/dependency_links.txt
Finance_JindowinData.egg-info/requires.txt
Finance_JindowinData.egg-info/top_level.txt
jdwdata/__init__.py
jdwdata/env.py
jdwdata/DataAPI/__init__.py
jdwdata/DataAPI/db/__init__.py
jdwdata/DataAPI/db/db_factory.py
jdwdata/DataAPI/db/fetch_engine.py
jdwdata/DataAPI/db/utilities.py
jdwdata/DataAPI/db/kd/__init__.py
jdwdata/DataAPI/db/kd/kd_engine.py
jdwdata/DataAPI/ddb/__init__.py
jdwdata/DataAPI/ddb/ddb_factory.py
jdwdata/DataAPI/ddb/fetch_engine.py
jdwdata/DataAPI/ddb/utilities.py
jdwdata/DataAPI/ddb/ch/__init__.py
jdwdata/DataAPI/ddb/ch/ch_engine.py
jdwdata/DataAPI/file/__init__.py
jdwdata/DataAPI/file/fetch_engine.py
jdwdata/DataAPI/file/file_factory.py
jdwdata/DataAPI/file/fl/__init__.py
jdwdata/DataAPI/file/fl/fl_engine.py
jdwdata/DataAPI/mg/__init__.py
jdwdata/DataAPI/mg/fetch_engine.py
jdwdata/DataAPI/mg/mg_factory.py
jdwdata/DataAPI/mg/mongodb.py
jdwdata/DataAPI/mg/kn/__init__.py
jdwdata/DataAPI/mg/kn/kn_engine.py
jdwdata/RetrievalAPI/__init__.py
jdwdata/RetrievalAPI/customized.py
jdwdata/RetrievalAPI/ddb_customized.py
jdwdata/RetrievalAPI/file_customized.py
jdwdata/SurfaceAPI/__init__.py
jdwdata/SurfaceAPI/dummy.py
jdwdata/SurfaceAPI/engine.py
jdwdata/SurfaceAPI/index_component.py
jdwdata/SurfaceAPI/index_market.py
jdwdata/SurfaceAPI/universe.py
jdwdata/SurfaceAPI/utilities.py
jdwdata/SurfaceAPI/yields.py
jdwdata/SurfaceAPI/futures/__init__.py
jdwdata/SurfaceAPI/futures/basic.py
jdwdata/SurfaceAPI/futures/classify.py
jdwdata/SurfaceAPI/futures/index_market.py
jdwdata/SurfaceAPI/futures/yields.py
jdwdata/SurfaceAPI/stock/__init__.py
jdwdata/SurfaceAPI/stock/industry.py
jdwdata/SurfaceAPI/stock/market_stock.py
jdwdata/SurfaceAPI/stock/risk_model.py
jdwdata/SurfaceAPI/stock/yields.py
jdwdata/config/__init__.py
jdwdata/config/export_cfg.py
jdwdata/config/mapping_cfg.py
jdwdata/kdutils/__init__.py
jdwdata/kdutils/logger.py
jdwdata/kdutils/singleton.py
requirements/py3.txt