Metadata-Version: 2.1
Name: Finance-JindowinData
Version: 0.0.9
Summary: JindowinData0.0.9
Home-page: https://github.com/flaght
Author: flaght
Author-email: flaght@gmail.com
